df3dbehav/augmentation.py
df3dbehav/dataset.py
df3dbehav/df3dbehav.py
df3dbehav/model.py
df3dbehav/tstrans.py
df3dbehav/utils.py
df3dbehav/data/__init__.py
df3dbehav/data/epoch=445-step=6243.ckpt
df3dbehav-0.24.dist-info/METADATA
df3dbehav-0.24.dist-info/WHEEL
df3dbehav-0.24.dist-info/entry_points.txt
df3dbehav-0.24.dist-info/top_level.txt
df3dbehav-0.24.dist-info/RECORD
